incplay/__init__.py
incplay/main.py
incplay-1.0.2.dist-info/LICENSE
incplay-1.0.2.dist-info/METADATA
incplay-1.0.2.dist-info/WHEEL
incplay-1.0.2.dist-info/top_level.txt
incplay-1.0.2.dist-info/RECORD
