Metadata-Version: 2.1
Name: incplay
Version: 1.0.2
Summary: A Hello World package
Home-page: https://github.com/zolinalexey/incplay
Author: INCOM? LLC
Author-email: zolinalexey@gmail.com
Classifier: Programming Language :: Python :: 3.8
Classifier: License :: OSI Approved :: MIT License
Classifier: Operating System :: OS Independent
Requires-Python: >=3.6
License-File: LICENSE
